{
  "version": "5.2.1",
  "flags": {},
  "shapes": [
    {
      "label": "rafaga",
      "points": [
        [
          81.48453608247422,
          245.36082474226805
        ],
        [
          82.51546391752578,
          297.9381443298969
        ],
        [
          98.49484536082474,
          294.3298969072165
        ],
        [
          111.89690721649484,
          255.15463917525773
        ],
        [
          111.89690721649484,
          236.08247422680412
        ],
        [
          118.5979381443299,
          221.1340206185567
        ],
        [
          123.23711340206185,
          202.57731958762886
        ],
        [
          108.8041237113402,
          201.03092783505153
        ],
        [
          91.79381443298968,
          211.8556701030928
        ]
      ],
      "group_id": null,
      "description": "",
      "shape_type": "polygon",
      "flags": {}
    }
  ],
  "imagePath": "img_2024-12-03_12.46.07_11153803_cam_H2674069.png",
  "imageData": null,
  "imageHeight": 500,
  "imageWidth": 464
}