{
  "version": "5.2.1",
  "flags": {},
  "shapes": [
    {
      "label": "rafaga",
      "points": [
        [
          72.72164948453607,
          253.60824742268042
        ],
        [
          73.23711340206185,
          226.8041237113402
        ],
        [
          109.31958762886597,
          193.29896907216494
        ],
        [
          131.48453608247422,
          206.18556701030928
        ],
        [
          116.02061855670104,
          226.28865979381442
        ],
        [
          104.68041237113403,
          248.96907216494844
        ],
        [
          103.64948453608247,
          272.680412371134
        ],
        [
          90.76288659793815,
          292.2680412371134
        ],
        [
          69.11340206185565,
          280.92783505154637
        ]
      ],
      "group_id": null,
      "description": "",
      "shape_type": "polygon",
      "flags": {}
    }
  ],
  "imagePath": "img_2024-12-03_12.36.33_11153705_cam_H2674069.png",
  "imageData": null,
  "imageHeight": 500,
  "imageWidth": 464
}