{
  "version": "5.2.1",
  "flags": {},
  "shapes": [
    {
      "label": "rafaga",
      "points": [
        [
          74.35158501440922,
          234.87031700288182
        ],
        [
          94.52449567723342,
          202.0172910662824
        ],
        [
          114.98559077809797,
          199.4236311239193
        ],
        [
          123.342939481268,
          211.52737752161383
        ],
        [
          118.44380403458213,
          228.53025936599423
        ],
        [
          110.95100864553314,
          245.53314121037462
        ],
        [
          112.39193083573487,
          262.53602305475505
        ],
        [
          93.65994236311239,
          279.2507204610951
        ],
        [
          82.70893371757924,
          275.21613832853023
        ]
      ],
      "group_id": null,
      "description": "",
      "shape_type": "polygon",
      "flags": {}
    }
  ],
  "imagePath": "img_2024-12-03_11.27.25_11152848_cam_H2674069.png",
  "imageData": null,
  "imageHeight": 500,
  "imageWidth": 464
}